{"batch_size":4,"layer_sizes":[2,3,1],"loss":1.2721762e-11,"loss_train":[0.035837647,0.0000031184916,7.5255846e-10,1.6496181e-10,9.4132986e-11,6.595059e-11,5.070113e-11,4.1068156e-11,3.4652076e-11,3.0034218e-11,2.64729e-11,2.374648e-11,2.1509582e-11,1.9726491e-11,1.8060024e-11,1.6575906e-11,1.5325855e-11,1.4362358e-11,1.3628334e-11,1.2721762e-11],"layers":[{"Dense":{"weights":{"rows":3,"columns":2,"data":[[-0.67372227,-0.3408953],[-0.7494612,0.20097649],[0.615041,-0.6891072]]},"biases":{"rows":3,"columns":1,"data":[[0.1810317],[-0.7354274],[-0.95146]]},"data":{"rows":3,"columns":1,"data":[[0.5451347],[0.32400486],[0.2785913]]},"loss":1.0,"activation_fn":"SIGMOID","learning_rate":0.1,"beta1":0.9,"beta2":0.999,"epsilon":1e-10,"time":0,"m_weights":{"rows":3,"columns":2,"data":[[0.0,0.0],[0.0,0.0],[0.0,0.0]]},"v_weights":{"rows":3,"columns":2,"data":[[0.0,0.0],[0.0,0.0],[0.0,0.0]]},"m_biases":{"rows":3,"columns":1,"data":[[0.0],[0.0],[0.0]]},"v_biases":{"rows":3,"columns":1,"data":[[0.0],[0.0],[0.0]]}}},{"Dense":{"weights":{"rows":1,"columns":3,"data":[[-623.7367,1307.991,752.4257]]},"biases":{"rows":1,"columns":1,"data":[[-305.94098]]},"data":{"rows":1,"columns":1,"data":[[0.0000035562032]]},"loss":0.000010630231,"activation_fn":"SIGMOID","learning_rate":0.1,"beta1":0.9,"beta2":0.999,"epsilon":1e-10,"time":800000,"m_weights":{"rows":1,"columns":3,"data":[[4.885266e-15,1.1849806e-14,-1.1301994e-15]]},"v_weights":{"rows":1,"columns":3,"data":[[2.9133227e-25,1.2952907e-25,1.2451875e-25]]},"m_biases":{"rows":1,"columns":1,"data":[[-1.2166029e-14]]},"v_biases":{"rows":1,"columns":1,"data":[[1.5233934e-24]]}}}],"uncompiled_layers":[{"DENSE":[2,"SIGMOID",0.1]},{"DENSE":[3,"SIGMOID",0.1]},{"DENSE":[1,"SIGMOID",0.1]}]}